[{"id":124,"title":"The Lord of the Rings: The Return of the King","genre":"Adventure, Fantasy, New Zealand, Usa","rating":"8.9","year":2003,"durasi":"03:21","image_link":"http://s0.lk21.org/wp-content/uploads/2015/12/film-the-lord-of-the-rings-the-return-of-the-king-2003.jpg","thriller_link":"https://www.youtube.com/embed/co9SNfJNDN8","movie_link":"http://indexmovie.me/play/out?movie=lord-rings-return-king-2003&size=","download_link":"http://indexmovie.me/lord-rings-return-king-2003/","sd360p":1,"sd480p":1,"hd720p":1,"hd1080p":0,"date":"2003-12-01","eps":0,"created_at":"2016-01-28","image_slide":null,"slide":0,"slide_number":0},{"id":330,"title":"Star Wars: Episode V - The Empire Strikes Back","genre":"Action, Adventure, Fantasy, Usa","rating":"8.8","year":1980,"durasi":"02:04","image_link":"http://s2.lk21.org/wp-content/uploads/2016/02/film-star-wars-episode-v-the-empire-strikes-back-1980.jpg","thriller_link":"https://www.youtube.com/embed/KwYa7UpoWtM","movie_link":"http://indexmovie.me/play/out?movie=star-wars-episode-v-empire-strikes-back-1980&size=","download_link":"http://indexmovie.me/star-wars-episode-v-empire-strikes-back-1980/","sd360p":1,"sd480p":1,"hd720p":1,"hd1080p":1,"date":"1980-01-01","eps":0,"created_at":"2017-02-05","image_slide":null,"slide":0,"slide_number":0},{"id":123,"title":"The Lord of the Rings: The Fellowship of the Ring","genre":"Adventure, Fantasy, New Zealand, Usa","rating":"8.8","year":2001,"durasi":"02:58","image_link":"http://s2.lk21.org/wp-content/uploads/2015/12/film-the-lord-of-the-rings-the-fellowship-of-the-ring-2001.jpg","thriller_link":"https://www.youtube.com/embed/V75dMMIW2B4","movie_link":"http://indexmovie.me/play/out?movie=the-lord-of-the-rings-the-fellowship-of-the-ring-2001&size=","download_link":"http://indexmovie.me/the-lord-of-the-rings-the-fellowship-of-the-ring-2001/","sd360p":1,"sd480p":1,"hd720p":1,"hd1080p":0,"date":"2001-12-20","eps":0,"created_at":"2016-01-28","image_slide":null,"slide":0,"slide_number":0},{"id":122,"title":"The Lord of the Rings: The Two Towers","genre":"Adventure, Fantasy, New Zealand, Usa","rating":"8.7","year":2002,"durasi":"02:59","image_link":"http://s2.lk21.org/wp-content/uploads/2015/12/film-the-lord-of-the-rings-the-two-towers-2002.jpg","thriller_link":"https://www.youtube.com/embed/LbfMDwc4azU","movie_link":"http://indexmovie.me/play/out?movie=lord-rings-two-towers-2002&size=","download_link":"http://indexmovie.me/lord-rings-two-towers-2002/","sd360p":1,"sd480p":1,"hd720p":1,"hd1080p":0,"date":"2002-12-18","eps":0,"created_at":"2016-01-28","image_slide":null,"slide":0,"slide_number":0},{"id":214,"title":"Star Wars: Episode IV - A New Hope","genre":"Action, Adventure, Fantasy, Usa","rating":"8.7","year":1977,"durasi":"02:01","image_link":"http://s1.lk21.org/wp-content/uploads/2015/12/film-star-wars-episode-iv-a-new-hope-1977.jpg","thriller_link":"https://www.youtube.com/embed/vZ734NWnAHA","movie_link":"http://indexmovie.me/play/out?movie=star-wars-episode-iv-a-new-hope-1977&size=","download_link":"http://indexmovie.me/star-wars-episode-iv-a-new-hope-1977/","sd360p":1,"sd480p":1,"hd720p":1,"hd1080p":0,"date":"1977-05-25","eps":0,"created_at":"2017-01-30","image_slide":null,"slide":0,"slide_number":0},{"id":78,"title":"Interstellar","genre":"Adventure, Drama, Sci-fi, Uk, Usa","rating":"8.6","year":2014,"durasi":"02:49","image_link":"http://s2.lk21.org/wp-content/uploads/2015/12/film-interstellar-2014.jpg","thriller_link":"https://www.youtube.com/embed/ePbKGoIGAXY","movie_link":"http://indexmovie.me/play/out?movie=interstellar-2014&size=","download_link":"http://indexmovie.me/interstellar-2014/","sd360p":1,"sd480p":1,"hd720p":1,"hd1080p":0,"date":"2014-11-05","eps":0,"created_at":"2016-01-28","image_slide":null,"slide":0,"slide_number":0},{"id":350,"title":"Hacksaw Ridge","genre":"Drama, History, War, Australia, Usa","rating":"8.5","year":2016,"durasi":"02:11","image_link":"http://s0.lk21.org/wp-content/uploads/2017/01/film-hacksaw-ridge-2016.jpg","thriller_link":"https://www.youtube.com/embed/s2-1hz1juBI","movie_link":"http://indexmovie.me/play/out?movie=hacksaw-ridge-2016&size=","download_link":"http://indexmovie.me/hacksaw-ridge-2016/","sd360p":1,"sd480p":1,"hd720p":1,"hd1080p":0,"date":"2016-11-04","eps":0,"created_at":"2017-02-09","image_slide":"https://images-na.ssl-images-amazon.com/images/M/MV5BMTg0ODc2NTUyOV5BMl5BanBnXkFtZTgwODEwNjc0MDI@._V1_SX1500_CR0,0,1500,999_AL_.jpg","slide":1,"slide_number":10},{"id":97,"title":"The Prestige","genre":"Drama, Mystery, Sci-fi, Uk, Usa","rating":"8.5","year":2006,"durasi":"02:10","image_link":"http://s2.lk21.org/wp-content/uploads/2016/01/film-the-prestige-2006.jpg","thriller_link":"https://www.youtube.com/embed/a1AqrIkD7vU","movie_link":"http://indexmovie.me/play/out?movie=the-prestige-2006&size=","download_link":"http://indexmovie.me/the-prestige-2006/","sd360p":1,"sd480p":1,"hd720p":1,"hd1080p":0,"date":"2006-10-19","eps":0,"created_at":"2016-01-28","image_slide":null,"slide":0,"slide_number":0},{"id":135,"title":"Hitting the Apex","genre":"Documentary, Usa","rating":"8.5","year":2015,"durasi":"02:18","image_link":"http://s1.lk21.org/wp-content/uploads/2016/07/film-hitting-the-apex-2015.jpg","thriller_link":"https://www.youtube.com/embed/fmT_vnJ1jzw","movie_link":"http://indexmovie.me/play/out?movie=hitting-apex-2015&size=","download_link":"http://indexmovie.me/hitting-apex-2015/","sd360p":1,"sd480p":1,"hd720p":1,"hd1080p":0,"date":"2015-09-02","eps":0,"created_at":"2016-01-28","image_slide":null,"slide":0,"slide_number":0},{"id":354,"title":"Manchester by the Sea","genre":"Drama, Usa","rating":"8.4","year":2016,"durasi":"02:15","image_link":"http://s1.lk21.org/wp-content/uploads/2017/02/film-manchester-by-the-sea-2016.jpg","thriller_link":"https://www.youtube.com/embed/gsVoD0pTge0","movie_link":"http://indexmovie.me/play/out?movie=manchester-sea-2016&size=","download_link":"http://indexmovie.me/manchester-sea-2016/","sd360p":1,"sd480p":1,"hd720p":1,"hd1080p":0,"date":"2016-11-18","eps":0,"created_at":"2017-02-10","image_slide":"none","slide":0,"slide_number":0},{"id":314,"title":"Arrival","genre":"Drama, Mystery, Sci-fi, Usa","rating":"8.3","year":2016,"durasi":"01:56","image_link":"http://s0.lk21.org/wp-content/uploads/2017/01/arrivalposter.jpg","thriller_link":"https://www.youtube.com/embed/gwqSi_ToNPs","movie_link":"http://indexmovie.me/play/out?movie=arrival-2016&size=","download_link":"http://indexmovie.me/arrival-2016/","sd360p":1,"sd480p":1,"hd720p":1,"hd1080p":0,"date":"2016-11-10","eps":0,"created_at":"2017-02-05","image_slide":"https://images-na.ssl-images-amazon.com/images/M/MV5BNzA4Mzg5OTY5Nl5BMl5BanBnXkFtZTgwMDk4ODg0MDI@._V1_UX477_CR0,0,477,268_AL_.jpg","slide":1,"slide_number":2},{"id":73,"title":"Deadpool","genre":"Action, Adventure, Comedy, Canada, Usa","rating":"8.1","year":2016,"durasi":"01:48","image_link":"http://s1.lk21.org/wp-content/uploads/2016/05/film-deadpool-2016.jpg","thriller_link":"https://www.youtube.com/embed/FyKWUTwSYAs","movie_link":"http://indexmovie.me/play/out?movie=deadpool-2016&size=","download_link":"http://indexmovie.me/deadpool-2016/","sd360p":1,"sd480p":1,"hd720p":1,"hd1080p":0,"date":"2016-02-09","eps":0,"created_at":"2016-01-28","image_slide":null,"slide":0,"slide_number":0},{"id":143,"title":"The Avengers","genre":"Action, Sci-fi, Thriller, Usa","rating":"8.1","year":2012,"durasi":"02:23","image_link":"http://s2.lk21.org/wp-content/uploads/2016/02/film-the-avengers-2012.jpg","thriller_link":"https://www.youtube.com/embed/eOrNdBpGMv8","movie_link":"http://indexmovie.me/play/out?movie=the-avengers-2012&size=","download_link":"http://indexmovie.me/the-avengers-2012/","sd360p":1,"sd480p":1,"hd720p":1,"hd1080p":0,"date":"2012-04-24","eps":0,"created_at":"2016-01-28","image_slide":null,"slide":0,"slide_number":0},{"id":180,"title":"Pirates of the Caribbean: The Curse of the Black Pearl","genre":"Action, Adventure, Fantasy, Usa","rating":"8.1","year":2003,"durasi":"02:23","image_link":"http://s2.lk21.org/wp-content/uploads/2015/12/film-pirates-of-the-caribbean-the-curse-of-the-black-pearl-2003.jpg","thriller_link":"https://www.youtube.com/embed/ZFCno8e-KuI","movie_link":"http://indexmovie.me/play/out?movie=pirates-caribbean-curse-black-pearl-2003&size=","download_link":"http://indexmovie.me/pirates-caribbean-curse-black-pearl-2003/","sd360p":1,"sd480p":1,"hd720p":1,"hd1080p":0,"date":"2003-07-09","eps":0,"created_at":"2016-01-28","image_slide":null,"slide":0,"slide_number":0},{"id":215,"title":"Star Wars 7: The Force Awakens","genre":"Action, Adventure, Fantasy, Usa","rating":"8.1","year":2015,"durasi":"02:16","image_link":"http://s0.lk21.org/wp-content/uploads/2015/12/film-star-wars-the-force-awakens-2015.jpg","thriller_link":"https://www.youtube.com/embed/OMOVFvcNfvE","movie_link":"http://indexmovie.me/play/out?movie=star-wars-7-force-awakens-2015&size=","download_link":"http://indexmovie.me/star-wars-7-force-awakens-2015/","sd360p":1,"sd480p":1,"hd720p":1,"hd1080p":0,"date":"2015-12-18","eps":0,"created_at":"2017-01-30","image_slide":null,"slide":0,"slide_number":0},{"id":313,"title":"Moana","genre":"Adventure, Animation, Comedy, Usa","rating":"8.0","year":2016,"durasi":"01:43","image_link":"http://s2.lk21.org/wp-content/uploads/2016/12/film-moana-2016.jpg","thriller_link":"https://www.youtube.com/embed/LKFuXETZUsI","movie_link":"http://indexmovie.me/play/out?movie=moana-2016&size=","download_link":"http://indexmovie.me/moana-2016/","sd360p":1,"sd480p":0,"hd720p":0,"hd1080p":0,"date":"2016-11-23","eps":0,"created_at":"2017-02-06","image_slide":"https://images-na.ssl-images-amazon.com/images/M/MV5BODcxNDUzNjM4Nl5BMl5BanBnXkFtZTgwMjIyODY2MDI@._V1_.jpg","slide":1,"slide_number":6},{"id":133,"title":"Captain America: Civil War","genre":"Action, Adventure, Sci-fi, Usa","rating":"8.0","year":2016,"durasi":"02:26","image_link":"http://s2.lk21.org/wp-content/uploads/2016/05/film-captain-america-civil-war-2016.jpg","thriller_link":"https://www.youtube.com/embed/43NWzay3W4s","movie_link":"http://indexmovie.me/play/out?movie=captain-america-civil-war-2016&size=","download_link":"http://indexmovie.me/captain-america-civil-war-2016/","sd360p":1,"sd480p":1,"hd720p":1,"hd1080p":0,"date":"2016-04-27","eps":0,"created_at":"2016-01-28","image_slide":null,"slide":0,"slide_number":0},{"id":136,"title":"X-Men: Days of Future Past","genre":"Action, Adventure, Sci-fi, Canada, Uk, Usa","rating":"8.0","year":2015,"durasi":"02:11","image_link":"http://s2.lk21.org/wp-content/uploads/2015/12/film-x-men-days-of-future-past-2014.jpg","thriller_link":"https://www.youtube.com/embed/gsjtg7m1MMM","movie_link":"http://indexmovie.me/play/out?movie=x-men-days-of-future-past-2014&size=","download_link":"http://indexmovie.me/x-men-days-of-future-past-2014/","sd360p":1,"sd480p":1,"hd720p":1,"hd1080p":0,"date":"2014-05-23","eps":0,"created_at":"2016-01-28","image_slide":null,"slide":0,"slide_number":0},{"id":22,"title":"Nocturnal Animals","genre":"Drama, Thriller, Usa","rating":"7.9","year":2016,"durasi":"01:56","image_link":"http://s0.lk21.org/wp-content/uploads/2016/12/film-nocturnal-animals-2016.jpg","thriller_link":"https://www.youtube.com/embed/8TmJFCakY2o","movie_link":"http://indexmovie.me/play/out?movie=nocturnal-animals-2016&size=","download_link":"http://indexmovie.me/nocturnal-animals-2016/","sd360p":1,"sd480p":1,"hd720p":1,"hd1080p":0,"date":"2016-11-04","eps":0,"created_at":"2016-11-04","image_slide":null,"slide":0,"slide_number":0},{"id":334,"title":"Justice League Dark","genre":"Action, Animation, Fantasy, Usa","rating":"7.9","year":2017,"durasi":"01:40","image_link":"http://s1.lk21.org/wp-content/uploads/2017/01/film-justice-league-dark-2017.jpg","thriller_link":"https://www.youtube.com/embed/cddLDL_kKOU","movie_link":"http://indexmovie.me/play/out?movie=justice-league-dark-2017&size=","download_link":"http://indexmovie.me/justice-league-dark-2017/","sd360p":1,"sd480p":1,"hd720p":1,"hd1080p":0,"date":"2017-01-24","eps":0,"created_at":"2017-02-05","image_slide":"https://images-na.ssl-images-amazon.com/images/M/MV5BMjA4NDMwODAxMV5BMl5BanBnXkFtZTgwNDIxNTc2MDI@._V1_UX477_CR0,0,477,268_AL_.jpg","slide":1,"slide_number":3},{"id":125,"title":"The Hobbit: An Unexpected Journey","genre":"Adventure, Fantasy, New Zealand, Usa","rating":"7.9","year":2012,"durasi":"02:49","image_link":"http://s1.lk21.org/wp-content/uploads/2015/12/film-the-hobbit-an-unexpected-journey-2012.jpg","thriller_link":"https://www.youtube.com/embed/dFQS8IKrUHA","movie_link":"http://indexmovie.me/play/out?movie=the-hobbit-an-unexpected-journey-2012&size=","download_link":"http://indexmovie.me/the-hobbit-an-unexpected-journey-2012/","sd360p":1,"sd480p":1,"hd720p":1,"hd1080p":0,"date":"2012-12-14","eps":0,"created_at":"2016-01-28","image_slide":null,"slide":0,"slide_number":0},{"id":126,"title":"The Hobbit: The Desolation of Smaug","genre":"Adventure, Fantasy, New Zealand, Usa","rating":"7.9","year":2013,"durasi":"02:41","image_link":"http://s0.lk21.org/wp-content/uploads/2015/12/film-the-hobbit-the-desolation-of-smaug-2013.jpg","thriller_link":"https://www.youtube.com/embed/BcB0znwAdmg","movie_link":"http://indexmovie.me/play/out?movie=hobbit-desolation-smaug-2013&size=","download_link":"http://indexmovie.me/hobbit-desolation-smaug-2013/","sd360p":1,"sd480p":1,"hd720p":1,"hd1080p":0,"date":"2013-12-13","eps":0,"created_at":"2016-01-28","image_slide":null,"slide":0,"slide_number":0},{"id":151,"title":"Iron Man","genre":"Action, Adventure, Sci-fi, Usa","rating":"7.9","year":2008,"durasi":"02:06","image_link":"http://s2.lk21.org/wp-content/uploads/2016/01/film-iron-man-2008.jpg","thriller_link":"https://www.youtube.com/embed/KAE5ymVLmZg","movie_link":"http://indexmovie.me/play/out?movie=iron-man-2008&size=","download_link":"http://indexmovie.me/iron-man-2008/","sd360p":1,"sd480p":1,"hd720p":1,"hd1080p":0,"date":"2008-05-02","eps":0,"created_at":"2016-01-28","image_slide":null,"slide":0,"slide_number":0},{"id":154,"title":"The World's Fastest Indian","genre":"Biography, Drama, Sport, Japan, New Zealand, Switzerland, Usa","rating":"7.9","year":2005,"durasi":"02:07","image_link":"http://s2.lk21.org/wp-content/uploads/2016/07/film-worlds-fastest-indian-2005.jpg","thriller_link":"https://www.youtube.com/embed/02Yy1vihIKs","movie_link":"http://indexmovie.me/play/out?movie=worlds-fastest-indian-2005&size=","download_link":"http://indexmovie.me/worlds-fastest-indian-2005/","sd360p":1,"sd480p":1,"hd720p":1,"hd1080p":0,"date":"2005-10-13","eps":0,"created_at":"2016-01-28","image_slide":null,"slide":0,"slide_number":0},{"id":188,"title":"Doctor Strange","genre":"Action, Adventure, Fantasy, Usa","rating":"7.9","year":2016,"durasi":"01:55","image_link":"http://s1.lk21.org/wp-content/uploads/2016/11/film-doctor-strange-2016.jpg","thriller_link":"https://www.youtube.com/embed/yrQ5gUrRSrc","movie_link":"http://indexmovie.me/play/out?movie=doctor-strange-2016&size=","download_link":"http://indexmovie.me/doctor-strange-2016/","sd360p":1,"sd480p":1,"hd720p":1,"hd1080p":1,"date":"2016-10-25","eps":0,"created_at":"2017-02-06","image_slide":"https://images-na.ssl-images-amazon.com/images/M/MV5BMTc0NDk0MjM1OF5BMl5BanBnXkFtZTgwMzY5MDAzMDI@._V1_SY250_CR15,0,444,250_AL_.jpg","slide":1,"slide_number":8},{"id":223,"title":"Before Midnight","genre":"Drama, Romance, Greece, Usa","rating":"7.9","year":2013,"durasi":"01:49","image_link":"http://s0.lk21.org/wp-content/uploads/2015/12/film-before-midnight-2013.jpg","thriller_link":"https://www.youtube.com/embed/euOJkb0U8vE","movie_link":"http://indexmovie.me/play/out?movie=before-midnight-2013&size=","download_link":"http://indexmovie.me/before-midnight-2013/","sd360p":1,"sd480p":1,"hd720p":1,"hd1080p":0,"date":"2013-06-14","eps":0,"created_at":"2017-01-30","image_slide":null,"slide":0,"slide_number":0},{"id":315,"title":"The Edge of Seventeen","genre":"Comedy, Drama, Usa","rating":"7.8","year":2016,"durasi":"01:44","image_link":"http://s0.lk21.org/wp-content/uploads/2017/02/film-the-edge-of-seventeen-2016.jpg","thriller_link":"https://www.youtube.com/embed/g2eR6j8eocE","movie_link":"http://indexmovie.me/play/out?movie=edge-seventeen-2016&size=","download_link":"http://indexmovie.me/edge-seventeen-2016/","sd360p":1,"sd480p":1,"hd720p":1,"hd1080p":0,"date":"2016-11-18","eps":0,"created_at":"2017-02-03","image_slide":null,"slide":0,"slide_number":0},{"id":137,"title":"Captain America: The Winter Soldier","genre":"Action, Adventure, Sci-fi, Usa","rating":"7.8","year":2014,"durasi":"02:16","image_link":"http://s1.lk21.org/wp-content/uploads/2016/02/film-captain-america-the-winter-soldier-2014.jpg","thriller_link":"https://www.youtube.com/embed/C5mNSbS9hi8","movie_link":"http://indexmovie.me/play/out?movie=captain-america-winter-soldier-2014&size=","download_link":"http://indexmovie.me/captain-america-winter-soldier-2014/","sd360p":1,"sd480p":1,"hd720p":1,"hd1080p":0,"date":"2014-03-20","eps":0,"created_at":"2016-01-28","image_slide":null,"slide":0,"slide_number":0},{"id":145,"title":"Fastest","genre":"Action, Documentary, Sport, Usa","rating":"7.8","year":2011,"durasi":"01:50","image_link":"http://s2.lk21.org/wp-content/uploads/2016/08/film-fastest-2011.jpg","thriller_link":"https://www.youtube.com/embed/Cq1f_UzflsI","movie_link":"http://indexmovie.me/play/out?movie=fastest-2011&size=","download_link":"http://indexmovie.me/fastest-2011/","sd360p":1,"sd480p":1,"hd720p":1,"hd1080p":0,"date":"2011-09-20","eps":0,"created_at":"2016-01-28","image_slide":null,"slide":0,"slide_number":0},{"id":147,"title":"X-Men: First Class","genre":"Action, Adventure, Sci-fi, Uk, Usa","rating":"7.8","year":2011,"durasi":"02:12","image_link":"http://s2.lk21.org/wp-content/uploads/2015/12/film-x-men-first-class-2011.jpg","thriller_link":"https://www.youtube.com/embed/o8ccSiH4olo","movie_link":"http://indexmovie.me/play/out?movie=x-men-first-class-2011&size=","download_link":"http://indexmovie.me/x-men-first-class-2011/","sd360p":1,"sd480p":1,"hd720p":1,"hd1080p":1,"date":"2011-05-24","eps":0,"created_at":"2016-01-28","image_slide":null,"slide":0,"slide_number":0},{"id":187,"title":"A Monster Calls","genre":"Drama, Fantasy, Spain, Usa","rating":"7.8","year":2016,"durasi":"01:48","image_link":"http://s2.lk21.org/wp-content/uploads/2017/01/film-a-monster-calls-2016.jpg","thriller_link":"https://www.youtube.com/embed/yrQ5gUrRSrc","movie_link":"http://indexmovie.me/play/out?movie=monster-calls-2016&size=","download_link":"http://indexmovie.me/monster-calls-2016/","sd360p":1,"sd480p":1,"hd720p":1,"hd1080p":0,"date":"2016-10-07","eps":0,"created_at":"2017-02-10","image_slide":"https://images-na.ssl-images-amazon.com/images/M/MV5BMzUyOTI1OTc2OV5BMl5BanBnXkFtZTgwMDEwNzM5MDI@._V1_CR0,59,640,360_AL_UX477_CR0,0,477,268_AL_.jpg","slide":0,"slide_number":0},{"id":35,"title":"The Accountant","genre":"Action, Crime, Drama, Usa","rating":"7.7","year":2016,"durasi":"02:08","image_link":"http://s0.lk21.org/wp-content/uploads/2016/12/film-the-accountant-2016.jpg","thriller_link":"https://www.youtube.com/embed/aNGhnNMSopI","movie_link":"http://indexmovie.me/play/out?movie=the-accountant-2016&size=","download_link":"http://indexmovie.me/the-accountant-2016/","sd360p":1,"sd480p":1,"hd720p":1,"hd1080p":0,"date":"2016-10-14","eps":0,"created_at":"2016-10-14","image_slide":null,"slide":0,"slide_number":0},{"id":98,"title":"Titanic","genre":"Drama, Romance, Usa","rating":"7.7","year":1997,"durasi":"03:14","image_link":"http://s1.lk21.org/wp-content/uploads/2016/01/film-titanic-1997.jpg","thriller_link":"https://www.youtube.com/embed/ZQ6klONCq4s","movie_link":"http://indexmovie.me/play/out?movie=titanic-1997&size=","download_link":"http://indexmovie.me/titanic-1997/","sd360p":1,"sd480p":1,"hd720p":1,"hd1080p":0,"date":"1997-12-19","eps":0,"created_at":"2016-01-28","image_slide":null,"slide":0,"slide_number":0},{"id":171,"title":"Fantastic Beasts and Where to Find Them","genre":"Adventure, Family, Fantasy, Uk, Usa","rating":"7.7","year":2016,"durasi":"02:13","image_link":"http://s1.lk21.org/wp-content/uploads/2016/11/film-fantastic-beasts-and-where-to-find-them-2016.jpg","thriller_link":"https://www.youtube.com/embed/FnZF82_3Cts","movie_link":"http://indexmovie.me/play/out?movie=fantastic-beasts-find-2016&size=","download_link":"http://indexmovie.me/fantastic-beasts-find-2016/","sd360p":1,"sd480p":1,"hd720p":1,"hd1080p":0,"date":"2016-11-16","eps":0,"created_at":"2016-01-28","image_slide":null,"slide":0,"slide_number":0},{"id":29,"title":"American Honey","genre":"Drama, Uk, Usa","rating":"7.6","year":2016,"durasi":"02:42","image_link":"http://s1.lk21.org/wp-content/uploads/2016/12/film-american-honey-2016.jpg","thriller_link":"https://www.youtube.com/embed/qz8UAEeT32o","movie_link":"http://indexmovie.me/play/out?movie=american-honey-2016&size=","download_link":"http://indexmovie.me/american-honey-2016/","sd360p":1,"sd480p":1,"hd720p":1,"hd1080p":0,"date":"2016-01-08","eps":0,"created_at":"2016-01-08","image_slide":null,"slide":0,"slide_number":0},{"id":68,"title":"Don't Breathe","genre":"Horror, Thriller, Usa","rating":"7.6","year":2016,"durasi":"01:28","image_link":"http://s0.lk21.org/wp-content/uploads/2016/09/film-dont-breathe-2016.jpg","thriller_link":"https://www.youtube.com/embed/76yBTNDB6vU","movie_link":"http://indexmovie.me/play/out?movie=dont-breathe-2016&size=","download_link":"http://indexmovie.me/dont-breathe-2016/","sd360p":1,"sd480p":1,"hd720p":1,"hd1080p":1,"date":"2016-08-25","eps":0,"created_at":"2016-01-28","image_slide":null,"slide":0,"slide_number":0},{"id":72,"title":"The Conjuring 2","genre":"Horror, Usa","rating":"7.6","year":2016,"durasi":"02:14","image_link":"http://s1.lk21.org/wp-content/uploads/2016/06/film-the-conjuring-2-2016.jpg","thriller_link":"https://www.youtube.com/embed/KyA9AtUOqRM","movie_link":"http://indexmovie.me/play/out?movie=conjuring-2-2016&size=","download_link":"http://indexmovie.me/conjuring-2-2016/","sd360p":1,"sd480p":1,"hd720p":1,"hd1080p":0,"date":"2016-06-08","eps":0,"created_at":"2016-01-28","image_slide":null,"slide":0,"slide_number":0},{"id":82,"title":"Fury","genre":"Action, Drama, War, China, Uk, Usa","rating":"7.6","year":2014,"durasi":"02:15","image_link":"http://s0.lk21.org/wp-content/uploads/2016/02/film-fury-2014.jpg","thriller_link":"https://www.youtube.com/embed/q94n3eWOWXM","movie_link":"http://indexmovie.me/play/out?movie=fury-2014&size=","download_link":"http://indexmovie.me/fury-2014/","sd360p":1,"sd480p":1,"hd720p":1,"hd1080p":0,"date":"2014-10-15","eps":0,"created_at":"2016-01-28","image_slide":null,"slide":0,"slide_number":0},{"id":128,"title":"The Hunger Games: Catching Fire","genre":"Adventure, Sci-fi, Thriller, Usa","rating":"7.6","year":2013,"durasi":"02:26","image_link":"http://s1.lk21.org/wp-content/uploads/2016/02/film-the-hunger-games-catching-fire-2013.jpg","thriller_link":"https://www.youtube.com/embed/jyPnQw_Lqds","movie_link":"http://indexmovie.me/play/out?movie=the-hunger-games-catching-fire-2013&size=","download_link":"http://indexmovie.me/the-hunger-games-catching-fire-2013/","sd360p":1,"sd480p":1,"hd720p":1,"hd1080p":0,"date":"2013-11-15","eps":0,"created_at":"2016-01-28","image_slide":null,"slide":0,"slide_number":0},{"id":43,"title":"Deepwater Horizon","genre":"Action, Drama, Thriller, Hong Kong, Usa","rating":"7.5","year":2016,"durasi":"01:47","image_link":"http://s1.lk21.org/wp-content/uploads/2016/11/film-deepwater-horizon-2016.jpg","thriller_link":"https://www.youtube.com/embed/8yASbM8M2vg","movie_link":"http://indexmovie.me/play/out?movie=deepwater-horizon-2016&size=","download_link":"http://indexmovie.me/deepwater-horizon-2016/","sd360p":1,"sd480p":1,"hd720p":1,"hd1080p":0,"date":"2016-09-29","eps":0,"created_at":"2016-01-28","image_slide":null,"slide":0,"slide_number":0},{"id":71,"title":"Me Before You","genre":"Drama, Romance, Usa","rating":"7.5","year":2016,"durasi":"01:33","image_link":"http://s0.lk21.org/wp-content/uploads/2016/07/film-me-before-you-2016.jpg","thriller_link":"https://www.youtube.com/embed/up7_B8x4Obs","movie_link":"http://indexmovie.me/play/out?movie=me-before-you-2016&size=","download_link":"http://indexmovie.me/me-before-you-2016/","sd360p":1,"sd480p":1,"hd720p":1,"hd1080p":0,"date":"2016-03-03","eps":0,"created_at":"2016-01-28","image_slide":null,"slide":0,"slide_number":0},{"id":344,"title":"Grease Live!","genre":"Musical, Romance, Usa","rating":"7.5","year":2016,"durasi":"03:00","image_link":"http://s0.lk21.org/wp-content/uploads/2017/02/film-grease-live-2016.jpg","thriller_link":"https://www.youtube.com/embed/7gZWGRD0Glg","movie_link":"http://indexmovie.me/play/out?movie=grease-live-2016&size=","download_link":"http://indexmovie.me/grease-live-2016/","sd360p":1,"sd480p":1,"hd720p":1,"hd1080p":0,"date":"2016-01-31","eps":0,"created_at":"2017-02-08","image_slide":"none","slide":0,"slide_number":0}]